iotawattpy/__init__.py
iotawattpy/connection.py
iotawattpy/const.py
iotawattpy/iotawatt.py
iotawattpy/sensor.py
ha_iotawattpy-0.1.2.dist-info/LICENSE
ha_iotawattpy-0.1.2.dist-info/METADATA
ha_iotawattpy-0.1.2.dist-info/WHEEL
ha_iotawattpy-0.1.2.dist-info/top_level.txt
ha_iotawattpy-0.1.2.dist-info/RECORD
